ultipro/__init__.py
ultipro/cli.py
ultipro/client.py
ultipro/helpers.py
ultipro/services/__init__.py
ultipro/services/bi_data.py
ultipro/services/bi_reports.py
ultipro/services/bi_stream.py
ultipro/services/employee_address.py
ultipro/services/employee_compensation.py
ultipro/services/employee_employment_information.py
ultipro/services/employee_job.py
ultipro/services/employee_person.py
ultipro/services/employee_phone_information.py
ultipro/services/employee_termination.py
ultipro/services/login.py
ultipro-0.0.3.dist-info/LICENSE
ultipro-0.0.3.dist-info/METADATA
ultipro-0.0.3.dist-info/WHEEL
ultipro-0.0.3.dist-info/entry_points.txt
ultipro-0.0.3.dist-info/top_level.txt
ultipro-0.0.3.dist-info/RECORD
