Metadata-Version: 2.1
Name: ultipro
Version: 0.0.3
Summary: Python Client for the UltiPro SOAP API
Home-page: https://github.com/puppetlabs/ultipro-soap-python
Author: Brian Call
Author-email: callbrian@gmail.com
License: Apache 2.0
Keywords: UltiPro,SOAP API,Wrapper,Client
Platform: UNKNOWN
Requires-Python: >=3.6
Requires-Dist: backoff
Requires-Dist: click
Requires-Dist: configparser
Requires-Dist: pandas
Requires-Dist: pandas-gbq
Requires-Dist: zeep
